lmtk/__init__.py
lmtk/__main__.py
lmtk/cli.py
lmtk/errors.py
lmtk/publish.py
lmtk/requirements.txt
lmtk/builtin/profiles/chat-delphi.yaml
lmtk/builtin/profiles/js-blank.yaml
lmtk/builtin/profiles/js-console.yaml
lmtk/builtin/profiles/js-game.yaml
lmtk/builtin/profiles/js-svg.yaml
lmtk/builtin/profiles/js-web.yaml
lmtk/builtin/profiles/jupyter-game.yaml
lmtk/config/__init__.py
lmtk/config/config.py
lmtk/config/folders.py
lmtk/config/profile.py
lmtk/jupyter/__init__.py
lmtk/jupyter/kernel.py
lmtk/jupyter/lmtk/__init__.py
lmtk/jupyter/lmtk/kernel.json
lmtk/llms/__init__.py
lmtk/llms/chat_gpt/__init__.py
lmtk/llms/chat_gpt/api.mjs
lmtk/llms/chat_gpt/chat_gpt.py
lmtk/llms/open_ai/__init__.py
lmtk/llms/open_ai/embedder.py
lmtk/llms/open_ai/embedding_manager.py
lmtk/llms/open_ai/gpt3.py
lmtk/llms/open_ai/utils.py
lmtk/modes/__init__.py
lmtk/modes/base_mode.py
lmtk/modes/chat_gpt.py
lmtk/modes/cowsay.py
lmtk/modes/echo.py
lmtk/modes/js_sandbox.py
lmtk/modes/lang_chain.py
lmtk/modes/raw_codex.py
lmtk/modes/raw_gpt.py
lmtk/modes/synth_chat.py
lmtk/repl/__init__.py
lmtk/repl/core.py
lmtk/repl/pretty.py
lmtk/repl/prompt.py
lmtk/repl/search.py
lmtk/repl/commands/__init__.py
lmtk/repl/commands/base_command.py
lmtk/repl/commands/command_manager.py
lmtk/repl/commands/normal_commands.py
lmtk/repl/commands/special_commands.py
lmtk/script/__init__.py
lmtk/script/__main__.py
lmtk/script/context.py
lmtk/script/helpers.py
lmtk/script/runtime.py
lmtk/script/section.py
lmtk/search/__init__.py
lmtk/search/engine.py
lmtk/search/store_manager.py
lmtk/search/indexers/__init__.py
lmtk/search/indexers/base.py
lmtk/search/indexers/file_system.py
lmtk/search/stores/__init__.py
lmtk/search/stores/base.py
lmtk/search/stores/simple.py
lmtk/threads/__init__.py
lmtk/threads/state_store.py
lmtk/threads/thread.py
lmtk/threads/thread_manager.py
lmtk/utils/__init__.py
lmtk/utils/editor.py
lmtk/utils/gist.py
lmtk/utils/loader.py
lmtk/utils/markdown.py
lmtk/utils/misc.py
lmtk/utils/printer.py
lmtk-0.4.32.dist-info/entry_points.txt
lmtk-0.4.32.dist-info/LICENSE
lmtk-0.4.32.dist-info/WHEEL
lmtk-0.4.32.dist-info/METADATA
lmtk-0.4.32.dist-info/RECORD
