Metadata-Version: 2.1
Name: lmtk
Version: 0.4.32
Summary: Command line REPL for GPT-based tools
Author-email: Lucas Hansen <lucashansen@gmail.com>
Requires-Python: >=3.9
Classifier: License :: OSI Approved :: MIT License
Requires-Dist: beautifulsoup4 >=4.0
Requires-Dist: dataclasses-json >=0.5
Requires-Dist: jsonpatch >=1.32
Requires-Dist: markdown-it-py[plugins] >=2.0
Requires-Dist: openai >=0.25
Requires-Dist: prompt_toolkit >=3.0
Requires-Dist: pyperclip >=1.0
Requires-Dist: requests >=2.0
Requires-Dist: rich >=12.0
Requires-Dist: tiktoken >=0.1
Requires-Dist: typer >=0.7
Requires-Dist: pyyaml >=6.0
Requires-Dist: guesslang-experimental >=2.2.3 ; extra == "extras"
Requires-Dist: ipykernel >=6.0 ; extra == "jupyter"
Project-URL: Home, https://github.com/veered/lmtk
Provides-Extra: extras
Provides-Extra: jupyter
